Metadata-Version: 2.1
Name: wrsi
Version: 0.1
Summary: Water requirement satisfaction index (wrsi) for crop calculator
Author: Farafehizoro Ramanjatonirina
License: UNKNOWN
Platform: UNKNOWN
License-File: LICENSE
